sruns_monitor/__init__.py
sruns_monitor/exceptions.py
sruns_monitor/firestore_utils.py
sruns_monitor/gcstorage_utils.py
sruns_monitor/logging_utils.py
sruns_monitor/monitor.py
sruns_monitor/schema.json
sruns_monitor/sqlite_utils.py
sruns_monitor/utils.py
sruns_monitor/scripts/__init__.py
sruns_monitor/scripts/launch_monitor.py
sruns_monitor/scripts/send_test_email.py
sruns_monitor/tests/__init__.py
sruns_monitor/tests/monitor_integration_tests.py
sruns_monitor/tests/test_sqlite_utils.py
sruns_monitor/tests/test_utils.py
sruns_monitor-1.2.0.data/scripts/launch_monitor.py
sruns_monitor-1.2.0.data/scripts/monitor_integration_tests.py
sruns_monitor-1.2.0.data/scripts/send_test_email.py
sruns_monitor-1.2.0.dist-info/METADATA
sruns_monitor-1.2.0.dist-info/WHEEL
sruns_monitor-1.2.0.dist-info/entry_points.txt
sruns_monitor-1.2.0.dist-info/top_level.txt
sruns_monitor-1.2.0.dist-info/RECORD
