Metadata-Version: 2.1
Name: sruns-monitor
Version: 1.2.0
Summary: Looks for new Illumina sequencing runs and tars them up into GCP storage
Home-page: https://pypi.org/project/sruns-monitor/
Author: Nathaniel Watson
Author-email: nathan.watson86@gmail.com
License: UNKNOWN
Project-URL: Read the Docs, https://sruns-monitor.readthedocs.io/en/latest
Keywords: archive sequencing runs monitor
Platform: UNKNOWN
Classifier: Programming Language :: Python :: 3
Classifier: License :: OSI Approved :: MIT License
Classifier: Operating System :: OS Independent
Requires-Dist: docutils
Requires-Dist: google-cloud-pubsub
Requires-Dist: google-cloud-firestore
Requires-Dist: google-cloud-storage
Requires-Dist: jsonschema
Requires-Dist: psutil
